content_analysis/__init__.py
content_analysis/common.py
content_analysis/constant.py
content_analysis/country.py
content_analysis/parallelizer.py
content_analysis/reach_estimation.py
content_analysis/topic_analyze.py
content_analysis/data/__init__.py
content_analysis/data/bio2topic.pickle
content_analysis/data/branded_hashtag.pickle
content_analysis/data/kwtree_brandname.pickle
content_analysis/data/kwtree_product.pickle
content_analysis/data/new_hashtag.pickle
content_analysis/data/product_type2topic.pickle
content_analysis/data/topic_hashtag.pickle
content_analysis1/__init__.py
content_analysis1/topic_analyze.py
content_analysis1/data/__init__.py
content_analysis_tool-0.1.4.dist-info/licenses/LICENSE
content_analysis_tool-0.1.4.dist-info/METADATA
content_analysis_tool-0.1.4.dist-info/WHEEL
content_analysis_tool-0.1.4.dist-info/top_level.txt
content_analysis_tool-0.1.4.dist-info/RECORD
