Metadata-Version: 2.4
Name: content-analysis-tool
Version: 0.1.4
Summary: Phân tích nội dung và nhận diện thương hiệu, chủ đề
Home-page: https://github.com/username/content-analysis-tool
Author: DongHoang
Author-email: hvdong1990@gmail.com
Classifier: Programming Language :: Python :: 3
Classifier: License :: OSI Approved :: MIT License
Classifier: Operating System :: OS Independent
License-File: LICENSE
Requires-Dist: ahocorapy
Requires-Dist: regex
Requires-Dist: statistics
Requires-Dist: pathlib
Dynamic: author
Dynamic: author-email
Dynamic: classifier
Dynamic: description
Dynamic: description-content-type
Dynamic: home-page
Dynamic: license-file
Dynamic: requires-dist
Dynamic: summary
